{
  "mirthandmalice:Forget": {
    "NAME": "Forget",
    "DESCRIPTIONS": [
      "Upon losing HP, apply #b",
      " #yWeak."
    ]
  },
  "mirthandmalice:Atrophy": {
    "NAME": "Atrophy",
    "DESCRIPTIONS": [
      "Loses #b",
      " HP when you debuff it."
    ]
  },
  "mirthandmalice:Excess": {
    "NAME": "Excess",
    "DESCRIPTIONS": [
      "At the start of your turn, lose #b",
      " HP, then remove all #yExcess.",
      "At the start of its turn, loses #b"
    ]
  },
  "mirthandmalice:Weight": {
    "NAME": "Weight",
    "DESCRIPTIONS": [
      "This enemy's #yVulnerable stacks additively until the end of the turn.",
      "This enemy's #yVulnerable stacks additively for #b",
      " turns."
    ]
  },
  "mirthandmalice:Volatile": {
    "NAME": "Volatile",
    "DESCRIPTIONS": [
      "On death, deals damage equal to half of its Max HP to ALL enemies."
    ]
  },
  "mirthandmalice:Record": {
    "NAME": "Record",
    "DESCRIPTIONS": [
      "Add a copy of the next card played to ",
      "Add a copy of the next #b",
      " cards played to ",
      " draw pile.",
      "your",
      "'s"
    ]
  },
  "mirthandmalice:Ruthless": {
    "NAME": "Ruthless",
    "DESCRIPTIONS": [
      "Whenever an enemy dies, gain #b",
      " #yStrength."
    ]
  },
  "mirthandmalice:Inhibition": {
    "NAME": "Inhibition",
    "DESCRIPTIONS": [
      "At the start of your turn, gain #b",
      " #ymirthandmalice:Seal."
    ]
  },
  "mirthandmalice:Execration": {
    "NAME": "Execration",
    "DESCRIPTIONS": [
      "Whenever you apply a debuff to an enemy, gain #b",
      " #yStrength."
    ]
  },
  "mirthandmalice:Seal": {
    "NAME": "Seal",
    "DESCRIPTIONS": [
      "Prevents the next time you would lose HP by spending it.",
      "Prevents the next #b",
      " times you would lose HP by spending it."
    ]
  },
  "mirthandmalice:Ignition": {
    "NAME": "Ignition",
    "DESCRIPTIONS": [
      "Whenever you would gain #yStrength, summon a #ymirthandmalice:Flame instead.",
      "Whenever you would gain #yStrength, summon #b",
      " #ymirthandmalice:Flames instead."
    ]
  }
}